{"cameraMode":{"drawMode":0,"name":"Shaded","section":"Shading Mode"},"sceneLighting":false,"audioPlay":false,"sceneViewState":{"m_AlwaysRefresh":false,"showFog":true,"showSkybox":false,"showFlares":true,"showImageEffects":true,"showParticleSystems":true,"showVisualEffectGraphs":true,"m_FxEnabled":true},"in2DMode":false,"pivot":{"x":-0.02415943145751953,"y":1.3099074363708497,"z":0.17048528790473939},"rotation":{"x":-0.1704736053943634,"y":-0.0032216005492955448,"z":0.0005664457567036152,"w":-0.9853666424751282},"size":1.3692561388015748,"orthographic":false}